exam_library/__init__.py
exam_library/my_code.py
exam_library_rqiza-0.1.dist-info/METADATA
exam_library_rqiza-0.1.dist-info/WHEEL
exam_library_rqiza-0.1.dist-info/top_level.txt
exam_library_rqiza-0.1.dist-info/RECORD
